my_krml_24996199/__init__.py
my_krml_24996199/app.py
my_krml_24996199/data/.gitkeep
my_krml_24996199/data/__init__.py
my_krml_24996199/data/make_dataset.py
my_krml_24996199/features/.gitkeep
my_krml_24996199/features/__init__.py
my_krml_24996199/features/build_features.py
my_krml_24996199/main.py
my_krml_24996199/models/.gitkeep
my_krml_24996199/models/__init__.py
my_krml_24996199/models/predict_model.py
my_krml_24996199/models/train_model.py
my_krml_24996199/visualization/.gitkeep
my_krml_24996199/visualization/__init__.py
my_krml_24996199/visualization/visualize.py
my_krml_24996199-0.1.49.dist-info/LICENSE
my_krml_24996199-0.1.49.dist-info/METADATA
my_krml_24996199-0.1.49.dist-info/WHEEL
my_krml_24996199-0.1.49.dist-info/RECORD
