Metadata-Version: 2.1
Name: my_krml_24996199
Version: 0.1.49
Summary: A package for doing great things!
License: MIT
Author: my_krml_24996199
Requires-Python: >=3.11.4,<4.0.0
Classifier: License :: OSI Approved :: MIT License
Classifier: Programming Language :: Python :: 3
Classifier: Programming Language :: Python :: 3.12
Requires-Dist: imbalanced-learn (>=0.12.3,<0.13.0)
Requires-Dist: joblib (>=1.4.2,<2.0.0)
Requires-Dist: lightgbm (>=4.5.0,<5.0.0)
Requires-Dist: matplotlib (>=3.9.2,<4.0.0)
Requires-Dist: pandas (==2.2.2)
Requires-Dist: scikit-learn (==1.5.1)
Requires-Dist: seaborn (>=0.13.2,<0.14.0)
Requires-Dist: xgboost (>=2.1.1,<3.0.0)
